ensembleclustering/ClusterEnsembles.py
ensembleclustering/__init__.py
ensembleclustering/kahypar_config/km1_kKaHyPar_sea20.ini
ensembleclustering/tests/__init__.py
ensembleclustering/tests/data/__init__.py
ensembleclustering/tests/data/base_clusters.csv
ensembleclustering/tests/data/create_test_data.py
ensembleclustering/tests/data/label_true.csv
ensembleclustering/tests/test_cspa.py
ensembleclustering/tests/test_hbgf.py
ensembleclustering/tests/test_hgpa.py
ensembleclustering/tests/test_mcla.py
ensembleclustering/tests/test_nmf.py
ensembleclustering/tests/test_utils.py
ensembleclustering-1.0.11.dist-info/LICENSE
ensembleclustering-1.0.11.dist-info/WHEEL
ensembleclustering-1.0.11.dist-info/METADATA
ensembleclustering-1.0.11.dist-info/RECORD
