Metadata-Version: 2.1
Name: ensembleclustering
Version: 1.0.11
Summary: 
Author: Takehiro Sano
Author-email: tsano430@gmail.com
Requires-Python: >=3.8,<4.0
Classifier: Programming Language :: Python :: 3
Classifier: Programming Language :: Python :: 3.10
Classifier: Programming Language :: Python :: 3.8
Classifier: Programming Language :: Python :: 3.9
Requires-Dist: kahypar (==1.1.3)
Requires-Dist: numpy (>=1.19.5,<2.0.0)
Requires-Dist: pymetis (==2020.1)
Requires-Dist: pytest (>=7.1.2,<8.0.0)
Requires-Dist: scikit-learn (>=1.0.1,<1.1.0)
Requires-Dist: scipy (>=1.5.0,<2.0.0)
